pdf2txt/__init__.py
pdf2txt/_cmap.py
pdf2txt/_encryption.py
pdf2txt/_page.py
pdf2txt/_protocols.py
pdf2txt/_reader.py
pdf2txt/_security.py
pdf2txt/_utils.py
pdf2txt/_version.py
pdf2txt/charts.py
pdf2txt/constants.py
pdf2txt/errors.py
pdf2txt/exceptions.py
pdf2txt/filters.py
pdf2txt/imutils.py
pdf2txt/pagerange.py
pdf2txt/settings.py
pdf2txt/table.py
pdf2txt/table_ml.py
pdf2txt/types.py
pdf2txt/utils.py
pdf2txt/version.py
pdf2txt/visualize.py
pdf2txt/xmp.py
pdf2txt/_codecs/__init__.py
pdf2txt/_codecs/adobe_glyphs.py
pdf2txt/_codecs/pdfdoc.py
pdf2txt/_codecs/std.py
pdf2txt/_codecs/symbol.py
pdf2txt/_codecs/zapfding.py
pdf2txt/core/__init__.py
pdf2txt/core/component.py
pdf2txt/core/document.py
pdf2txt/core/filtering.py
pdf2txt/core/indexer.py
pdf2txt/core/page.py
pdf2txt/core/paragraph.py
pdf2txt/core/search.py
pdf2txt/core/token.py
pdf2txt/core/tree.py
pdf2txt/core/word.py
pdf2txt/doc_analyzer/__init__.py
pdf2txt/doc_analyzer/connected_components.py
pdf2txt/doc_analyzer/image_analyzer.py
pdf2txt/doc_analyzer/imageprocessor.py
pdf2txt/doc_analyzer/img.py
pdf2txt/doc_analyzer/region.py
pdf2txt/doc_analyzer/text_segmenter.py
pdf2txt/generic/__init__.py
pdf2txt/generic/_annotations.py
pdf2txt/generic/_base.py
pdf2txt/generic/_data_structures.py
pdf2txt/generic/_fit.py
pdf2txt/generic/_outline.py
pdf2txt/generic/_rectangle.py
pdf2txt/generic/_utils.py
pdf2txt/simple_reader/__init__.py
pdf2txt/simple_reader/_cmap.py
pdf2txt/simple_reader/_encryption.py
pdf2txt/simple_reader/_page.py
pdf2txt/simple_reader/_protocols.py
pdf2txt/simple_reader/_reader.py
pdf2txt/simple_reader/_security.py
pdf2txt/simple_reader/_utils.py
pdf2txt/simple_reader/_version.py
pdf2txt/simple_reader/constants.py
pdf2txt/simple_reader/errors.py
pdf2txt/simple_reader/filters.py
pdf2txt/simple_reader/pagerange.py
pdf2txt/simple_reader/types.py
pdf2txt/simple_reader/xmp.py
pdf2txt/simple_reader/_codecs/__init__.py
pdf2txt/simple_reader/_codecs/adobe_glyphs.py
pdf2txt/simple_reader/_codecs/pdfdoc.py
pdf2txt-0.7.14.dist-info/METADATA
pdf2txt-0.7.14.dist-info/WHEEL
pdf2txt-0.7.14.dist-info/top_level.txt
pdf2txt-0.7.14.dist-info/RECORD
